{
    "name": "swizzle",
    "description": "Displays information about a swizzle",
    "dm_permission": false,
    "options": [
        {
            "name": "image",
            "description": "Recolor images to one or more swizzles",
            "type": 1,
            "options":  [
                {
                    "name": "image1",
                    "description": "an image to swizzle",
                    "type": 11,
                    "required": true
                },
                {
                    "name": "swizzles",
                    "description": "List of swizzles; ie. 1,3,9,15 or 1-6 or 1-6,12-17 or 4",
                    "type": 3,
                    "required": false
                },
                {
                    "name": "image2",
                    "description": "another image to swizzle",
                    "type": 11,
                    "required": false
                },
                {
                    "name": "image3",
                    "description": "another image to swizzle",
                    "type": 11,
                    "required": false
                },
                {
                    "name": "image4",
                    "description": "another image to swizzle",
                    "type": 11,
                    "required": false
                },
                {
                    "name": "hidden",
                    "description": "Hide response from other users.",
                    "type": 3,
                    "required": false,
                    "choices": [
                        {
                            "name": "hide",
                            "value": "hide"
                        },
                        {
                            "name": "show",
                            "value": "show"
                        }
                    ]
                }
            ]
        },
        {
            "name": "search",
            "description": "Swizzles images in game data files",
            "type": 1,
            "options":  [
                {
                    "name": "query",
                    "description": "query for searching game data files",
                    "type": 3,
                    "required": true
                },
                {
                    "name": "swizzles",
                    "description": "List of swizzles; ie. 1,3,9,15 or 1-6 or 1-6,12-17 or 4",
                    "type": 3,
                    "required": false
                },
                {
                    "name": "hidden",
                    "description": "Hide response from other users.",
                    "type": 3,
                    "required": false,
                    "choices": [
                        {
                            "name": "hide",
                            "value": "hide"
                        },
                        {
                            "name": "show",
                            "value": "show"
                        }
                    ]
                }
            ]
        }
    ]
}
